pyhap/__init__.py
pyhap/accessory.py
pyhap/characteristic.py
pyhap/config.py
pyhap/exception.py
pyhap/http_server.py
pyhap/pair.py
pyhap/pyhap.py
pyhap/route.py
pyhap/service.py
pyhap/srp.py
pyhap/tlv.py
pyhap/util.py
pyhap/characteristics/__init__.py
pyhap/characteristics/accessory_identifier.py
pyhap/characteristics/administrator_only_access.py
pyhap/characteristics/air_particulate_density.py
pyhap/characteristics/air_particulate_size.py
pyhap/characteristics/air_quality.py
pyhap/characteristics/audio_feedback.py
pyhap/characteristics/battery_level.py
pyhap/characteristics/brightness.py
pyhap/characteristics/carbon_dioxide_detected.py
pyhap/characteristics/carbon_dioxide_level.py
pyhap/characteristics/carbon_dioxide_peak_level.py
pyhap/characteristics/carbon_monoxide_detected.py
pyhap/characteristics/carbon_monoxide_level.py
pyhap/characteristics/carbon_monoxide_peak_level.py
pyhap/characteristics/category.py
pyhap/characteristics/charging_state.py
pyhap/characteristics/configure_bridged_accessory.py
pyhap/characteristics/configure_bridged_accessory_status.py
pyhap/characteristics/contact_sensor_state.py
pyhap/characteristics/cooling_threshold_temperature.py
pyhap/characteristics/current_ambient_light_level.py
pyhap/characteristics/current_door_state.py
pyhap/characteristics/current_heating_cooling_state.py
pyhap/characteristics/current_horizontal_tilt_angle.py
pyhap/characteristics/current_position.py
pyhap/characteristics/current_relative_humidity.py
pyhap/characteristics/current_temperature.py
pyhap/characteristics/current_time.py
pyhap/characteristics/current_vertical_tilt_angle.py
pyhap/characteristics/day_of_the_week.py
pyhap/characteristics/discover_bridged_accessories.py
pyhap/characteristics/discovered_bridged_accessories.py
pyhap/characteristics/firmware_revision.py
pyhap/characteristics/hardware_revision.py
pyhap/characteristics/heating_threshold_temperature.py
pyhap/characteristics/hold_position.py
pyhap-0.1.1.dist-info/DESCRIPTION.rst
pyhap-0.1.1.dist-info/METADATA
pyhap-0.1.1.dist-info/RECORD
pyhap-0.1.1.dist-info/WHEEL
pyhap-0.1.1.dist-info/metadata.json
pyhap-0.1.1.dist-info/top_level.txt
