Metadata-Version: 1.2
Name: pyhap
Version: 0.1.1
Summary: Python implementation of HomeKit Accessory Protocol
Home-page: https://github.com/condemil/pyhap
Author: Dmitry Budaev
Author-email: UNKNOWN
License: MIT
Platform: UNKNOWN
Classifier: Intended Audience :: Developers
Classifier: License :: OSI Approved :: MIT License
Classifier: Programming Language :: Python
Classifier: Programming Language :: Python :: 3
Classifier: Programming Language :: Python :: 3.6
Classifier: Topic :: Home Automation
Classifier: Topic :: Software Development :: Libraries
Requires-Python: >=3.6.0
